[
  {
    "id": 22402,
    "name": "Libram of Grace",
    "slot": 17,
    "notEnchantable": true
  },
  {
    "id": 22400,
    "name": "Libram of Truth",
    "slot": 17,
    "notEnchantable": true
  },
  {
    "id": 22401,
    "name": "Libram of Hope",
    "slot": 17,
    "notEnchantable": true
  },
  {
    "id": 23006,
    "name": "Libram of Light",
    "slot": 17,
    "notEnchantable": true
  },
  {
    "id": 23201,
    "name": "Libram of Divinity",
    "slot": 17,
    "notEnchantable": true
  },
  {
    "id": 23203,
    "name": "Libram of Fervor",
    "slot": 17,
    "notEnchantable": true
  },
  {
    "id": 24386,
    "name": "Libram of Saints Departed",
    "slot": 17,
    "notEnchantable": true
  },
  {
    "id": 25644,
    "name": "Blessed Book of Nagrand",
    "slot": 17,
    "notEnchantable": true
  },
  {
    "id": 27484,
    "name": "Libram of Avengement",
    "slot": 17,
    "notEnchantable": true
  },
  {
    "id": 27917,
    "name": "Libram of the Eternal Rest",
    "slot": 17,
    "notEnchantable": true
  },
  {
    "id": 27983,
    "name": "Libram of Zeal",
    "slot": 17,
    "notEnchantable": true
  },
  {
    "id": 27949,
    "name": "Libram of Zeal",
    "slot": 17,
    "notEnchantable": true
  },
  {
    "id": 28065,
    "name": "Libram of Wracking",
    "slot": 17,
    "notEnchantable": true
  },
  {
    "id": 28296,
    "name": "Libram of the Lightbringer",
    "slot": 17,
    "notEnchantable": true
  },
  {
    "id": 28356,
    "name": "Gladiator\u0027s Libram of Justice",
    "slot": 17,
    "notEnchantable": true
  },
  {
    "id": 28592,
    "name": "Libram of Souls Redeemed",
    "slot": 17,
    "notEnchantable": true
  },
  {
    "id": 29388,
    "name": "Libram of Repentance",
    "slot": 17,
    "notEnchantable": true
  },
  {
    "id": 30063,
    "name": "Libram of Absolute Truth",
    "slot": 17,
    "notEnchantable": true
  },
  {
    "id": 31033,
    "name": "Libram of Righteous Power",
    "slot": 17,
    "notEnchantable": true
  },
  {
    "id": 32368,
    "name": "Tome of the Lightbringer",
    "slot": 17,
    "notEnchantable": true
  },
  {
    "id": 33077,
    "name": "Merciless Gladiator\u0027s Libram of Justice",
    "slot": 17,
    "notEnchantable": true
  },
  {
    "id": 33502,
    "name": "Libram of Mending",
    "slot": 17,
    "notEnchantable": true
  },
  {
    "id": 33504,
    "name": "Libram of Divine Purpose",
    "slot": 17,
    "notEnchantable": true
  },
  {
    "id": 33503,
    "name": "Libram of Divine Judgement",
    "slot": 17,
    "notEnchantable": true
  },
  {
    "id": 33842,
    "name": "Vengeful Gladiator\u0027s Libram of Justice",
    "slot": 17,
    "notEnchantable": true
  },
  {
    "id": 33936,
    "name": "Gladiator\u0027s Libram of Fortitude",
    "slot": 17,
    "notEnchantable": true
  },
  {
    "id": 33937,
    "name": "Merciless Gladiator\u0027s Libram of Fortitude",
    "slot": 17,
    "notEnchantable": true
  },
  {
    "id": 33938,
    "name": "Vengeful Gladiator\u0027s Libram of Fortitude",
    "slot": 17,
    "notEnchantable": true
  },
  {
    "id": 33949,
    "name": "Merciless Gladiator\u0027s Libram of Vengeance",
    "slot": 17,
    "notEnchantable": true
  },
  {
    "id": 33950,
    "name": "Vengeful Gladiator\u0027s Libram of Vengeance",
    "slot": 17,
    "notEnchantable": true
  },
  {
    "id": 33948,
    "name": "Gladiator\u0027s Libram of Vengeance",
    "slot": 17,
    "notEnchantable": true
  },
  {
    "id": 35039,
    "name": "Brutal Gladiator\u0027s Libram of Fortitude",
    "slot": 17,
    "notEnchantable": true
  },
  {
    "id": 35040,
    "name": "Brutal Gladiator\u0027s Libram of Justice",
    "slot": 17,
    "notEnchantable": true
  },
  {
    "id": 35041,
    "name": "Brutal Gladiator\u0027s Libram of Vengeance",
    "slot": 17,
    "notEnchantable": true
  }
]