[
  {
    "id": 22345,
    "name": "Totem of Rebirth",
    "slot": 17,
    "notEnchantable": true
  },
  {
    "id": 22395,
    "name": "Totem of Rage",
    "slot": 17,
    "notEnchantable": true
  },
  {
    "id": 22396,
    "name": "Totem of Life",
    "slot": 17,
    "notEnchantable": true
  },
  {
    "id": 23005,
    "name": "Totem of Flowing Water",
    "slot": 17,
    "notEnchantable": true
  },
  {
    "id": 23200,
    "name": "Totem of Sustaining",
    "slot": 17,
    "notEnchantable": true
  },
  {
    "id": 23199,
    "name": "Totem of the Storm",
    "slot": 17,
    "notEnchantable": true
  },
  {
    "id": 24413,
    "name": "Totem of the Thunderhead",
    "slot": 17,
    "notEnchantable": true
  },
  {
    "id": 25645,
    "name": "Totem of the Plains",
    "slot": 17,
    "notEnchantable": true
  },
  {
    "id": 27544,
    "name": "Totem of Spontaneous Regrowth",
    "slot": 17,
    "notEnchantable": true
  },
  {
    "id": 27815,
    "name": "Totem of the Astral Winds",
    "slot": 17,
    "notEnchantable": true
  },
  {
    "id": 27984,
    "name": "Totem of Impact",
    "slot": 17,
    "notEnchantable": true
  },
  {
    "id": 28066,
    "name": "Totem of Lightning",
    "slot": 17,
    "notEnchantable": true
  },
  {
    "id": 27947,
    "name": "Totem of Impact",
    "slot": 17,
    "notEnchantable": true
  },
  {
    "id": 28248,
    "name": "Totem of the Void",
    "slot": 17,
    "notEnchantable": true
  },
  {
    "id": 28357,
    "name": "Gladiator\u0027s Totem of the Third Wind",
    "slot": 17,
    "notEnchantable": true
  },
  {
    "id": 28523,
    "name": "Totem of Healing Rains",
    "slot": 17,
    "notEnchantable": true
  },
  {
    "id": 29389,
    "name": "Totem of the Pulsing Earth",
    "slot": 17,
    "notEnchantable": true
  },
  {
    "id": 30023,
    "name": "Totem of the Maelstrom",
    "slot": 17,
    "notEnchantable": true
  },
  {
    "id": 31031,
    "name": "Stormfury Totem",
    "slot": 17,
    "notEnchantable": true
  },
  {
    "id": 32330,
    "name": "Totem of Ancestral Guidance",
    "slot": 17,
    "notEnchantable": true
  },
  {
    "id": 33078,
    "name": "Merciless Gladiator\u0027s Totem of the Third Wind",
    "slot": 17,
    "notEnchantable": true
  },
  {
    "id": 33507,
    "name": "Stonebreaker\u0027s Totem",
    "slot": 17,
    "notEnchantable": true
  },
  {
    "id": 33506,
    "name": "Skycall Totem",
    "slot": 17,
    "notEnchantable": true
  },
  {
    "id": 33505,
    "name": "Totem of Living Water",
    "slot": 17,
    "notEnchantable": true
  },
  {
    "id": 33843,
    "name": "Vengeful Gladiator\u0027s Totem of the Third Wind",
    "slot": 17,
    "notEnchantable": true
  },
  {
    "id": 33951,
    "name": "Gladiator\u0027s Totem of Survival",
    "slot": 17,
    "notEnchantable": true
  },
  {
    "id": 33939,
    "name": "Gladiator\u0027s Totem of Indomitability",
    "slot": 17,
    "notEnchantable": true
  },
  {
    "id": 33941,
    "name": "Vengeful Gladiator\u0027s Totem of Indomitability",
    "slot": 17,
    "notEnchantable": true
  },
  {
    "id": 33953,
    "name": "Vengeful Gladiator\u0027s Totem of Survival",
    "slot": 17,
    "notEnchantable": true
  },
  {
    "id": 33940,
    "name": "Merciless Gladiator\u0027s Totem of Indomitability",
    "slot": 17,
    "notEnchantable": true
  },
  {
    "id": 33952,
    "name": "Merciless Gladiator\u0027s Totem of Survival",
    "slot": 17,
    "notEnchantable": true
  },
  {
    "id": 35105,
    "name": "Brutal Gladiator\u0027s Totem of Survival",
    "slot": 17,
    "notEnchantable": true
  },
  {
    "id": 35106,
    "name": "Brutal Gladiator\u0027s Totem of the Third Wind",
    "slot": 17,
    "notEnchantable": true
  },
  {
    "id": 35104,
    "name": "Brutal Gladiator\u0027s Totem of Indomitability",
    "slot": 17,
    "notEnchantable": true
  }
]