[
  {
    "id": 11743,
    "name": "Rockfist",
    "slot": 16
  },
  {
    "id": 11744,
    "name": "Bloodfist",
    "slot": 16
  },
  {
    "id": 13198,
    "name": "Hurd Smasher",
    "slot": 16
  },
  {
    "id": 18462,
    "name": "Jagged Bone Fist",
    "slot": 16
  },
  {
    "id": 22317,
    "name": "Lefty\u0027s Brass Knuckle",
    "slot": 16
  },
  {
    "id": 25193,
    "name": "Deathclaw Talons",
    "slot": 16,
    "randomEnchantment": true
  },
  {
    "id": 25194,
    "name": "Serpent\u0027s Fangs",
    "slot": 16,
    "randomEnchantment": true
  },
  {
    "id": 25195,
    "name": "Diamond Tipped Claws",
    "slot": 16,
    "randomEnchantment": true
  },
  {
    "id": 25192,
    "name": "Gutrippers",
    "slot": 16,
    "randomEnchantment": true
  },
  {
    "id": 25538,
    "name": "Sporeling Claw",
    "slot": 16
  },
  {
    "id": 25764,
    "name": "Mag\u0027hari Fury Brand",
    "slot": 16
  }
]